VSD_riskV/week1/Day5/mux_generate.v
// This is the module under test, provided by the user.
// It's a 4-to-1 multiplexer implemented with a for loop.
module mux_generate (
    input i0, input i1, input i2, input i3,
    input [1:0] sel,
    output reg y
);
wire [3:0] i_int;
assign i_int = {i3, i2, i1, i0};
integer k;

always @(*) begin
    for (k = 0; k < 4; k = k + 1) begin
        if (k == sel) begin
            y = i_int[k];
        end
    end
end
endmodule

// This is the testbench module for the mux_generate.
// It uses an initial block to apply test vectors and a generate block
// to demonstrate its usage.
module mux_generate_tb;

    // Declare signals for the DUT inputs and outputs
    reg i0, i1, i2, i3;
    reg [1:0] sel;
    wire y;

    // Instantiate the module under test (DUT)
    mux_generate dut (
        .i0(i0),
        .i1(i1),
        .i2(i2),
        .i3(i3),
        .sel(sel),
        .y(y)
    );

    // Initial block for generating the stimulus and controlling simulation
    initial begin
        // Open the VCD file for waveform dumping
        $dumpfile("mux_generate.vcd");
        // Dump all signals in the current scope
        $dumpvars(0, mux_generate_tb);

        // Initialize inputs
        i0 = 0;
        i1 = 0;
        i2 = 0;
        i3 = 0;
        sel = 2'b00;

        // Apply a series of test vectors with delays to simulate time
        #10;
        $display("Time = %0t: i0=%b, i1=%b, i2=%b, i3=%b, sel=%b, y=%b", $time, i0, i1, i2, i3, sel, y);

        // Test case 1: select i0
        i0 = 1; i1 = 0; i2 = 0; i3 = 0; sel = 2'b00;
        #10;
        $display("Time = %0t: i0=%b, i1=%b, i2=%b, i3=%b, sel=%b, y=%b", $time, i0, i1, i2, i3, sel, y);

        // Test case 2: select i1
        i0 = 0; i1 = 1; i2 = 0; i3 = 0; sel = 2'b01;
        #10;
        $display("Time = %0t: i0=%b, i1=%b, i2=%b, i3=%b, sel=%b, y=%b", $time, i0, i1, i2, i3, sel, y);

        // Test case 3: select i2
        i0 = 0; i1 = 0; i2 = 1; i3 = 0; sel = 2'b10;
        #10;
        $display("Time = %0t: i0=%b, i1=%b, i2=%b, i3=%b, sel=%b, y=%b", $time, i0, i1, i2, i3, sel, y);

        // Test case 4: select i3
        i0 = 0; i1 = 0; i2 = 0; i3 = 1; sel = 2'b11;
        #10;
        $display("Time = %0t: i0=%b, i1=%b, i2=%b, i3=%b, sel=%b, y=%b", $time, i0, i1, i2, i3, sel, y);

        // Test all inputs being high
        i0 = 1; i1 = 1; i2 = 1; i3 = 1;
        #10;
        sel = 2'b00;
        #10;
        $display("Time = %0t: sel=%b, y=%b", $time, sel, y);
        sel = 2'b01;
        #10;
        $display("Time = %0t: sel=%b, y=%b", $time, sel, y);
        sel = 2'b10;
        #10;
        $display("Time = %0t: sel=%b, y=%b", $time, sel, y);
        sel = 2'b11;
        #10;
        $display("Time = %0t: sel=%b, y=%b", $time, sel, y);

        // End the simulation
        $finish;
    end

    // Example of a generate block
    // This part is for demonstrating the usage of `generate`.
    // It's not directly related to the mux functionality, but fulfills the request.
    genvar i;
    generate
        for (i = 0; i < 4; i = i + 1) begin : my_gen_block
            reg [7:0] my_array;
            initial my_array = i;
        end
    endgenerate

endmodule

VSD_riskV/week1/Day5/mux_generate.vcd
$date
	Fri Sep 26 10:32:11 2025
$end
$version
	Icarus Verilog
$end
$timescale
	1s
$end
$scope module mux_generate_tb $end
$var wire 1 ! y $end
$var reg 1 " i0 $end
$var reg 1 # i1 $end
$var reg 1 $ i2 $end
$var reg 1 % i3 $end
$var reg 2 & sel [1:0] $end
$scope begin my_gen_block[0] $end
$var parameter 2 ' i $end
$var reg 8 ( my_array [7:0] $end
$upscope $end
$scope begin my_gen_block[1] $end
$var parameter 2 ) i $end
$var reg 8 * my_array [7:0] $end
$upscope $end
$scope begin my_gen_block[2] $end
$var parameter 3 + i $end
$var reg 8 , my_array [7:0] $end
$upscope $end
$scope begin my_gen_block[3] $end
$var parameter 3 - i $end
$var reg 8 . my_array [7:0] $end
$upscope $end
$scope module dut $end
$var wire 1 " i0 $end
$var wire 1 # i1 $end
$var wire 1 $ i2 $end
$var wire 1 % i3 $end
$var wire 2 / sel [1:0] $end
$var wire 4 0 i_int [3:0] $end
$var reg 1 ! y $end
$var integer 32 1 k [31:0] $end
$upscope $end
$upscope $end
$enddefinitions $end
$comment Show the parameter values. $end
$dumpall
b11 -
b10 +
b1 )
b0 '
$end
#0
$dumpvars
b100 1
b0 0
b0 /
b11 .
b10 ,
b1 *
b0 (
b0 &
0%
0$
0#
0"
0!
$end
#10
1!
b100 1
b1 0
1"
#20
b100 1
b1 &
b1 /
1#
b10 0
0"
#30
b100 1
b10 &
b10 /
1$
b100 0
0#
#40
b100 1
b11 &
b11 /
1%
b1000 0
0$
#50
b100 1
1$
1#
b1111 0
1"
#60
b100 1
b0 &
b0 /
#70
b100 1
b1 &
b1 /
#80
b100 1
b10 &
b10 /
#90
b100 1
b11 &
b11 /
