VSD_riskV/week1/Day2/D_ff/dff_asyncres.v
module dff_asyncres (input clk, input async_reset, input d, output reg q);
  always @ (posedge clk, posedge async_reset)
    if (async_reset)
      q <= 1'b0;
    else
      q <= d;
endmodule

VSD_riskV/week1/Day2/D_ff/dff_asyncres_tb.v
// Testbench for the dff_asyncres module
`timescale 1ns / 1ps

module dff_asyncres_tb;

  // Inputs
  reg clk;
  reg async_reset;
  reg d;

  // Outputs
  wire q;

  // Instantiate the Unit Under Test (UUT)
  dff_asyncres UUT (
    .clk(clk),
    .async_reset(async_reset),
    .d(d),
    .q(q)
  );

  // Clock generation
  initial begin
    clk = 0;
    forever #5 clk = ~clk; // 10 ns period
  end

  // Test sequence
  initial begin
    // Dump waves to VCD file
    $dumpfile("dff_asyncres.vcd");
    $dumpvars(0, dff_asyncres_tb);

    // Initialize inputs
    async_reset = 1'b0;
    d = 1'b0;

    // Wait for a few clock cycles for stability
    #20;

    // Test normal operation
    d = 1'b1; // d changes, q will change on next posedge clk
    #10;
    d = 1'b0; // d changes, q will change on next posedge clk
    #10;
    d = 1'b1;
    #10;

    // Test asynchronous reset
    // Reset happens immediately, not waiting for the clock edge
    async_reset = 1'b1;
    d = 1'b0; // change d just to show it doesn't matter
    #5; // Wait for the reset to take effect
    async_reset = 1'b0; // Release the reset
    #5;

    // Test a final normal operation
    d = 1'b1;
    #10;
    
    $finish; // End simulation
  end
endmodule

VSD_riskV/week1/Day2/D_ff/dff_asyncres.vcd
$date
	Mon Sep 22 11:26:21 2025
$end
$version
	Icarus Verilog
$end
$timescale
	1ps
$end
$scope module dff_asyncres_tb $end
$var wire 1 ! q $end
$var reg 1 " async_reset $end
$var reg 1 # clk $end
$var reg 1 $ d $end
$scope module UUT $end
$var wire 1 " async_reset $end
$var wire 1 # clk $end
$var wire 1 $ d $end
$var reg 1 ! q $end
$upscope $end
$upscope $end
$enddefinitions $end
$comment Show the parameter values. $end
$dumpall
$end
#0
$dumpvars
0$
0#
0"
x!
$end
#5000
0!
1#
#10000
0#
#15000
1#
#20000
0#
1$
#25000
1!
1#
#30000
0#
0$
#35000
0!
1#
#40000
0#
1$
#45000
1!
1#
#50000
0!
0#
0$
1"
#55000
1#
0"
#60000
0#
1$
#65000
1!
1#
